odoo/addons/hr_timesheet_sheet_begin_end/README.rst
odoo/addons/hr_timesheet_sheet_begin_end/__init__.py
odoo/addons/hr_timesheet_sheet_begin_end/__manifest__.py
odoo/addons/hr_timesheet_sheet_begin_end/i18n/cs_CZ.po
odoo/addons/hr_timesheet_sheet_begin_end/i18n/de.po
odoo/addons/hr_timesheet_sheet_begin_end/i18n/es.po
odoo/addons/hr_timesheet_sheet_begin_end/i18n/fr.po
odoo/addons/hr_timesheet_sheet_begin_end/i18n/hr_timesheet_sheet_begin_end.pot
odoo/addons/hr_timesheet_sheet_begin_end/i18n/it.po
odoo/addons/hr_timesheet_sheet_begin_end/i18n/nl_NL.po
odoo/addons/hr_timesheet_sheet_begin_end/i18n/sv.po
odoo/addons/hr_timesheet_sheet_begin_end/i18n/sv_SE.po
odoo/addons/hr_timesheet_sheet_begin_end/readme/CONTRIBUTORS.rst
odoo/addons/hr_timesheet_sheet_begin_end/readme/DESCRIPTION.rst
odoo/addons/hr_timesheet_sheet_begin_end/static/description/icon.png
odoo/addons/hr_timesheet_sheet_begin_end/static/description/index.html
odoo/addons/hr_timesheet_sheet_begin_end/views/hr_timesheet_sheet.xml
odoo_addon_hr_timesheet_sheet_begin_end-15.0.1.0.0.6.dist-info/METADATA
odoo_addon_hr_timesheet_sheet_begin_end-15.0.1.0.0.6.dist-info/WHEEL
odoo_addon_hr_timesheet_sheet_begin_end-15.0.1.0.0.6.dist-info/top_level.txt
odoo_addon_hr_timesheet_sheet_begin_end-15.0.1.0.0.6.dist-info/RECORD
