Metadata-Version: 2.1
Name: odoo-addon-hr-timesheet-sheet-begin-end
Version: 15.0.1.0.0.6
Summary: Timesheet Sheet - Begin/End Hours
Home-page: https://github.com/OCA/timesheet
Author: Camptocamp, Tecnativa, Odoo Community Association (OCA)
Author-email: support@odoo-community.org
License: AGPL-3
Platform: UNKNOWN
Classifier: Programming Language :: Python
Classifier: Framework :: Odoo
Classifier: Framework :: Odoo :: 15.0
Classifier: License :: OSI Approved :: GNU Affero General Public License v3
Requires-Python: >=3.8
Requires-Dist: odoo-addon-hr-timesheet-begin-end <15.1dev,>=15.0dev
Requires-Dist: odoo-addon-hr-timesheet-sheet <15.1dev,>=15.0dev
Requires-Dist: odoo <15.1dev,>=15.0a
